Metadata-Version: 2.1
Name: django-postgres-createdb
Version: 2020.7.1
Summary: create postgres database
Home-page: https://github.com/andrewp-as-is/django-postgres-createdb.py
License: Unlicense
Keywords: django postgres create
Platform: UNKNOWN
Classifier: Framework :: Django
Classifier: License :: Public Domain
Classifier: Operating System :: OS Independent
Classifier: Programming Language :: Python :: 3
